LICENSE
README.md
pyproject.toml
bragir/__init__.py
bragir/__main__.py
bragir/client.py
bragir/commands.py
bragir/config.py
bragir/file.py
bragir/languages.py
bragir/messages.py
bragir/path.py
bragir/post_processing.py
bragir/time.py
bragir/timer.py
bragir/audio/__init__.py
bragir/audio/chunking.py
bragir/audio/grouping.py
bragir/constants/__init__.py
bragir/constants/ai.py
bragir/constants/files.py
bragir/constants/format_specs.py
bragir/files/__init__.py
bragir/files/file.py
bragir/files/operations.py
bragir/logging_configs/__init__.py
bragir/logging_configs/debug.json
bragir/logging_configs/info.json
bragir/spinner/__init__.py
bragir/spinner/spinner.py
bragir/srt/__init__.py
bragir/srt/srt_part.py
bragir/tracing/__init__.py
bragir/tracing/logger.py
bragir/tracing/stratergies.py
bragir/transcription/__init__.py
bragir/transcription/transcription.py
bragir/translation/__init__.py
bragir/translation/translation.py
tests/__init__.py
tests/file_test.py
tests/help_test.py
tests/test_post_processing.py
tests/time_test.py
tests/tracing/logging_test.py
tests/translation/translation_test.py
bragir-1.4.5.dist-info/METADATA
bragir-1.4.5.dist-info/WHEEL
bragir-1.4.5.dist-info/entry_points.txt
bragir-1.4.5.dist-info/licenses/LICENSE
bragir-1.4.5.dist-info/RECORD
