Metadata-Version: 2.4
Name: bragir
Version: 1.4.5
Summary: Add your description here
License-File: LICENSE
Requires-Python: >=3.12
Requires-Dist: click>=8.1.7
Requires-Dist: openai>=1.54.4
Requires-Dist: pydantic>=2.9.2
Requires-Dist: pydub>=0.25.1
Requires-Dist: ruff>=0.7.3
